PyUtilToolKit/__init__.py
PyUtilToolKit/util_log.py
pyCustomUtilToolKits-0.0.2.dist-info/METADATA
pyCustomUtilToolKits-0.0.2.dist-info/WHEEL
pyCustomUtilToolKits-0.0.2.dist-info/top_level.txt
pyCustomUtilToolKits-0.0.2.dist-info/RECORD
