Metadata-Version: 2.2
Name: pyCustomUtilToolKits
Version: 0.0.2
Summary: Python Custom Utils
Author: MysteriousMan
Author-email: 
License: GPLv3
Keywords: kit
Classifier: Programming Language :: Python :: 3
Classifier: License :: OSI Approved :: GNU General Public License v3 (GPLv3)
Classifier: Operating System :: OS Independent
Requires-Python: >=3.10
Dynamic: author
Dynamic: classifier
Dynamic: description
Dynamic: description-content-type
Dynamic: keywords
Dynamic: license
Dynamic: requires-python
Dynamic: summary
